simple_password/__init__.py
simple_password/generator.py
simple_password_gen-0.1.dist-info/METADATA
simple_password_gen-0.1.dist-info/WHEEL
simple_password_gen-0.1.dist-info/top_level.txt
simple_password_gen-0.1.dist-info/RECORD
