Metadata-Version: 2.4
Name: simple_password-gen
Version: 0.1
Summary: کتابخانه‌ای ساده برای تولید پسورد تصادفی در پایتون
Home-page: https://github.com/yourusername/simple_password
Author: Your Name
Author-email: your.email@example.com
Classifier: Programming Language :: Python :: 3
Classifier: License :: OSI Approved :: MIT License
Requires-Python: >=3.6
Dynamic: author
Dynamic: author-email
Dynamic: classifier
Dynamic: description
Dynamic: description-content-type
Dynamic: home-page
Dynamic: requires-python
Dynamic: summary
